goquantdata/__init__.py
goquantdata/exceptions.py
goquantdata/local_client.py
goquantdata/local/__init__.py
goquantdata/local/private_config.py
goquantdata/local/datasource/__init__.py
goquantdata/local/datasource/datasource.py
goquantdata/local/datasource/ds_alpha_vantage.py
goquantdata/local/datasource/ds_jqdata.py
goquantdata/local/datasource/ds_quandl.py
goquantdata/local/datasource/ds_tushare.py
goquantdata/local/datasource/ds_yahoo.py
goquantdata/local/datasource/get_ids.py
goquantdata/local/db/__init__.py
goquantdata/local/db/build_db.py
goquantdata/local/db/read_db.py
goquantdata/util/__init__.py
goquantdata/util/logger.py
goquantdata/util/util.py
goquantdata-0.0.6.dist-info/METADATA
goquantdata-0.0.6.dist-info/WHEEL
goquantdata-0.0.6.dist-info/top_level.txt
goquantdata-0.0.6.dist-info/RECORD
